{"nodes": [{"id": "users_lion_nutstore_files_\u6211\u7684\u575a\u679c\u4e91_flylion_ai\u9879\u76ee\u5f00\u53d1_\u4e03\u4e2a\u4e60\u60ef\u6668\u8bfb\u8425_admin_src_tests_helpers_mock_helpers_ts", "label": "mock-helpers.ts", "file_type": "code", "source_file": "/Users/lion/Nutstore Files/\u6211\u7684\u575a\u679c\u4e91/flylion/AI\u9879\u76ee\u5f00\u53d1/\u4e03\u4e2a\u4e60\u60ef\u6668\u8bfb\u8425/admin/src/tests/helpers/mock-helpers.ts", "source_location": "L1"}, {"id": "helpers_mock_helpers_createmockresponse", "label": "createMockResponse()", "file_type": "code", "source_file": "/Users/lion/Nutstore Files/\u6211\u7684\u575a\u679c\u4e91/flylion/AI\u9879\u76ee\u5f00\u53d1/\u4e03\u4e2a\u4e60\u60ef\u6668\u8bfb\u8425/admin/src/tests/helpers/mock-helpers.ts", "source_location": "L13"}, {"id": "helpers_mock_helpers_createmockapisuccess", "label": "createMockApiSuccess()", "file_type": "code", "source_file": "/Users/lion/Nutstore Files/\u6211\u7684\u575a\u679c\u4e91/flylion/AI\u9879\u76ee\u5f00\u53d1/\u4e03\u4e2a\u4e60\u60ef\u6668\u8bfb\u8425/admin/src/tests/helpers/mock-helpers.ts", "source_location": "L41"}, {"id": "helpers_mock_helpers_createmockapierror", "label": "createMockApiError()", "file_type": "code", "source_file": "/Users/lion/Nutstore Files/\u6211\u7684\u575a\u679c\u4e91/flylion/AI\u9879\u76ee\u5f00\u53d1/\u4e03\u4e2a\u4e60\u60ef\u6668\u8bfb\u8425/admin/src/tests/helpers/mock-helpers.ts", "source_location": "L50"}, {"id": "helpers_mock_helpers_mockapiget", "label": "mockApiGet()", "file_type": "code", "source_file": "/Users/lion/Nutstore Files/\u6211\u7684\u575a\u679c\u4e91/flylion/AI\u9879\u76ee\u5f00\u53d1/\u4e03\u4e2a\u4e60\u60ef\u6668\u8bfb\u8425/admin/src/tests/helpers/mock-helpers.ts", "source_location": "L59"}, {"id": "helpers_mock_helpers_mockapipost", "label": "mockApiPost()", "file_type": "code", "source_file": "/Users/lion/Nutstore Files/\u6211\u7684\u575a\u679c\u4e91/flylion/AI\u9879\u76ee\u5f00\u53d1/\u4e03\u4e2a\u4e60\u60ef\u6668\u8bfb\u8425/admin/src/tests/helpers/mock-helpers.ts", "source_location": "L66"}, {"id": "helpers_mock_helpers_mockapiput", "label": "mockApiPut()", "file_type": "code", "source_file": "/Users/lion/Nutstore Files/\u6211\u7684\u575a\u679c\u4e91/flylion/AI\u9879\u76ee\u5f00\u53d1/\u4e03\u4e2a\u4e60\u60ef\u6668\u8bfb\u8425/admin/src/tests/helpers/mock-helpers.ts", "source_location": "L73"}, {"id": "helpers_mock_helpers_mockapipatch", "label": "mockApiPatch()", "file_type": "code", "source_file": "/Users/lion/Nutstore Files/\u6211\u7684\u575a\u679c\u4e91/flylion/AI\u9879\u76ee\u5f00\u53d1/\u4e03\u4e2a\u4e60\u60ef\u6668\u8bfb\u8425/admin/src/tests/helpers/mock-helpers.ts", "source_location": "L80"}, {"id": "helpers_mock_helpers_mockapidelete", "label": "mockApiDelete()", "file_type": "code", "source_file": "/Users/lion/Nutstore Files/\u6211\u7684\u575a\u679c\u4e91/flylion/AI\u9879\u76ee\u5f00\u53d1/\u4e03\u4e2a\u4e60\u60ef\u6668\u8bfb\u8425/admin/src/tests/helpers/mock-helpers.ts", "source_location": "L87"}, {"id": "helpers_mock_helpers_mockapifailure", "label": "mockApiFailure()", "file_type": "code", "source_file": "/Users/lion/Nutstore Files/\u6211\u7684\u575a\u679c\u4e91/flylion/AI\u9879\u76ee\u5f00\u53d1/\u4e03\u4e2a\u4e60\u60ef\u6668\u8bfb\u8425/admin/src/tests/helpers/mock-helpers.ts", "source_location": "L94"}, {"id": "helpers_mock_helpers_createmockstoregetter", "label": "createMockStoreGetter()", "file_type": "code", "source_file": "/Users/lion/Nutstore Files/\u6211\u7684\u575a\u679c\u4e91/flylion/AI\u9879\u76ee\u5f00\u53d1/\u4e03\u4e2a\u4e60\u60ef\u6668\u8bfb\u8425/admin/src/tests/helpers/mock-helpers.ts", "source_location": "L105"}, {"id": "helpers_mock_helpers_createmockstoreaction", "label": "createMockStoreAction()", "file_type": "code", "source_file": "/Users/lion/Nutstore Files/\u6211\u7684\u575a\u679c\u4e91/flylion/AI\u9879\u76ee\u5f00\u53d1/\u4e03\u4e2a\u4e60\u60ef\u6668\u8bfb\u8425/admin/src/tests/helpers/mock-helpers.ts", "source_location": "L112"}, {"id": "helpers_mock_helpers_createmockstoremutation", "label": "createMockStoreMutation()", "file_type": "code", "source_file": "/Users/lion/Nutstore Files/\u6211\u7684\u575a\u679c\u4e91/flylion/AI\u9879\u76ee\u5f00\u53d1/\u4e03\u4e2a\u4e60\u60ef\u6668\u8bfb\u8425/admin/src/tests/helpers/mock-helpers.ts", "source_location": "L119"}, {"id": "helpers_mock_helpers_createmockstore", "label": "createMockStore()", "file_type": "code", "source_file": "/Users/lion/Nutstore Files/\u6211\u7684\u575a\u679c\u4e91/flylion/AI\u9879\u76ee\u5f00\u53d1/\u4e03\u4e2a\u4e60\u60ef\u6668\u8bfb\u8425/admin/src/tests/helpers/mock-helpers.ts", "source_location": "L126"}, {"id": "helpers_mock_helpers_createmockrouter", "label": "createMockRouter()", "file_type": "code", "source_file": "/Users/lion/Nutstore Files/\u6211\u7684\u575a\u679c\u4e91/flylion/AI\u9879\u76ee\u5f00\u53d1/\u4e03\u4e2a\u4e60\u60ef\u6668\u8bfb\u8425/admin/src/tests/helpers/mock-helpers.ts", "source_location": "L138"}, {"id": "helpers_mock_helpers_createmockrouteparams", "label": "createMockRouteParams()", "file_type": "code", "source_file": "/Users/lion/Nutstore Files/\u6211\u7684\u575a\u679c\u4e91/flylion/AI\u9879\u76ee\u5f00\u53d1/\u4e03\u4e2a\u4e60\u60ef\u6668\u8bfb\u8425/admin/src/tests/helpers/mock-helpers.ts", "source_location": "L151"}, {"id": "helpers_mock_helpers_createmocklocalstorage", "label": "createMockLocalStorage()", "file_type": "code", "source_file": "/Users/lion/Nutstore Files/\u6211\u7684\u575a\u679c\u4e91/flylion/AI\u9879\u76ee\u5f00\u53d1/\u4e03\u4e2a\u4e60\u60ef\u6668\u8bfb\u8425/admin/src/tests/helpers/mock-helpers.ts", "source_location": "L163"}, {"id": "helpers_mock_helpers_createmocksessionstorage", "label": "createMockSessionStorage()", "file_type": "code", "source_file": "/Users/lion/Nutstore Files/\u6211\u7684\u575a\u679c\u4e91/flylion/AI\u9879\u76ee\u5f00\u53d1/\u4e03\u4e2a\u4e60\u60ef\u6668\u8bfb\u8425/admin/src/tests/helpers/mock-helpers.ts", "source_location": "L198"}, {"id": "helpers_mock_helpers_mockwindowalert", "label": "mockWindowAlert()", "file_type": "code", "source_file": "/Users/lion/Nutstore Files/\u6211\u7684\u575a\u679c\u4e91/flylion/AI\u9879\u76ee\u5f00\u53d1/\u4e03\u4e2a\u4e60\u60ef\u6668\u8bfb\u8425/admin/src/tests/helpers/mock-helpers.ts", "source_location": "L233"}, {"id": "helpers_mock_helpers_mockconsolelog", "label": "mockConsoleLog()", "file_type": "code", "source_file": "/Users/lion/Nutstore Files/\u6211\u7684\u575a\u679c\u4e91/flylion/AI\u9879\u76ee\u5f00\u53d1/\u4e03\u4e2a\u4e60\u60ef\u6668\u8bfb\u8425/admin/src/tests/helpers/mock-helpers.ts", "source_location": "L242"}, {"id": "helpers_mock_helpers_mockconsoleerror", "label": "mockConsoleError()", "file_type": "code", "source_file": "/Users/lion/Nutstore Files/\u6211\u7684\u575a\u679c\u4e91/flylion/AI\u9879\u76ee\u5f00\u53d1/\u4e03\u4e2a\u4e60\u60ef\u6668\u8bfb\u8425/admin/src/tests/helpers/mock-helpers.ts", "source_location": "L246"}, {"id": "helpers_mock_helpers_mockconsolewarn", "label": "mockConsoleWarn()", "file_type": "code", "source_file": "/Users/lion/Nutstore Files/\u6211\u7684\u575a\u679c\u4e91/flylion/AI\u9879\u76ee\u5f00\u53d1/\u4e03\u4e2a\u4e60\u60ef\u6668\u8bfb\u8425/admin/src/tests/helpers/mock-helpers.ts", "source_location": "L250"}, {"id": "helpers_mock_helpers_waitfor", "label": "waitFor()", "file_type": "code", "source_file": "/Users/lion/Nutstore Files/\u6211\u7684\u575a\u679c\u4e91/flylion/AI\u9879\u76ee\u5f00\u53d1/\u4e03\u4e2a\u4e60\u60ef\u6668\u8bfb\u8425/admin/src/tests/helpers/mock-helpers.ts", "source_location": "L257"}, {"id": "helpers_mock_helpers_delay", "label": "delay()", "file_type": "code", "source_file": "/Users/lion/Nutstore Files/\u6211\u7684\u575a\u679c\u4e91/flylion/AI\u9879\u76ee\u5f00\u53d1/\u4e03\u4e2a\u4e60\u60ef\u6668\u8bfb\u8425/admin/src/tests/helpers/mock-helpers.ts", "source_location": "L276"}, {"id": "helpers_mock_helpers_createmockhttpinterceptor", "label": "createMockHttpInterceptor()", "file_type": "code", "source_file": "/Users/lion/Nutstore Files/\u6211\u7684\u575a\u679c\u4e91/flylion/AI\u9879\u76ee\u5f00\u53d1/\u4e03\u4e2a\u4e60\u60ef\u6668\u8bfb\u8425/admin/src/tests/helpers/mock-helpers.ts", "source_location": "L283"}, {"id": "helpers_mock_helpers_resetallmocks", "label": "resetAllMocks()", "file_type": "code", "source_file": "/Users/lion/Nutstore Files/\u6211\u7684\u575a\u679c\u4e91/flylion/AI\u9879\u76ee\u5f00\u53d1/\u4e03\u4e2a\u4e60\u60ef\u6668\u8bfb\u8425/admin/src/tests/helpers/mock-helpers.ts", "source_location": "L297"}, {"id": "helpers_mock_helpers_restoreallmocks", "label": "restoreAllMocks()", "file_type": "code", "source_file": "/Users/lion/Nutstore Files/\u6211\u7684\u575a\u679c\u4e91/flylion/AI\u9879\u76ee\u5f00\u53d1/\u4e03\u4e2a\u4e60\u60ef\u6668\u8bfb\u8425/admin/src/tests/helpers/mock-helpers.ts", "source_location": "L304"}], "edges": [{"source": "users_lion_nutstore_files_\u6211\u7684\u575a\u679c\u4e91_flylion_ai\u9879\u76ee\u5f00\u53d1_\u4e03\u4e2a\u4e60\u60ef\u6668\u8bfb\u8425_admin_src_tests_helpers_mock_helpers_ts", "target": "vitest", "relation": "imports_from", "context": "import", "confidence": "EXTRACTED", "source_file": "/Users/lion/Nutstore Files/\u6211\u7684\u575a\u679c\u4e91/flylion/AI\u9879\u76ee\u5f00\u53d1/\u4e03\u4e2a\u4e60\u60ef\u6668\u8bfb\u8425/admin/src/tests/helpers/mock-helpers.ts", "source_location": "L7", "weight": 1.0}, {"source": "users_lion_nutstore_files_\u6211\u7684\u575a\u679c\u4e91_flylion_ai\u9879\u76ee\u5f00\u53d1_\u4e03\u4e2a\u4e60\u60ef\u6668\u8bfb\u8425_admin_src_tests_helpers_mock_helpers_ts", "target": "helpers_mock_helpers_createmockresponse", "relation": "contains", "confidence": "EXTRACTED", "source_file": "/Users/lion/Nutstore Files/\u6211\u7684\u575a\u679c\u4e91/flylion/AI\u9879\u76ee\u5f00\u53d1/\u4e03\u4e2a\u4e60\u60ef\u6668\u8bfb\u8425/admin/src/tests/helpers/mock-helpers.ts", "source_location": "L13", "weight": 1.0}, {"source": "users_lion_nutstore_files_\u6211\u7684\u575a\u679c\u4e91_flylion_ai\u9879\u76ee\u5f00\u53d1_\u4e03\u4e2a\u4e60\u60ef\u6668\u8bfb\u8425_admin_src_tests_helpers_mock_helpers_ts", "target": "helpers_mock_helpers_createmockapisuccess", "relation": "contains", "confidence": "EXTRACTED", "source_file": "/Users/lion/Nutstore Files/\u6211\u7684\u575a\u679c\u4e91/flylion/AI\u9879\u76ee\u5f00\u53d1/\u4e03\u4e2a\u4e60\u60ef\u6668\u8bfb\u8425/admin/src/tests/helpers/mock-helpers.ts", "source_location": "L41", "weight": 1.0}, {"source": "users_lion_nutstore_files_\u6211\u7684\u575a\u679c\u4e91_flylion_ai\u9879\u76ee\u5f00\u53d1_\u4e03\u4e2a\u4e60\u60ef\u6668\u8bfb\u8425_admin_src_tests_helpers_mock_helpers_ts", "target": "helpers_mock_helpers_createmockapierror", "relation": "contains", "confidence": "EXTRACTED", "source_file": "/Users/lion/Nutstore Files/\u6211\u7684\u575a\u679c\u4e91/flylion/AI\u9879\u76ee\u5f00\u53d1/\u4e03\u4e2a\u4e60\u60ef\u6668\u8bfb\u8425/admin/src/tests/helpers/mock-helpers.ts", "source_location": "L50", "weight": 1.0}, {"source": "users_lion_nutstore_files_\u6211\u7684\u575a\u679c\u4e91_flylion_ai\u9879\u76ee\u5f00\u53d1_\u4e03\u4e2a\u4e60\u60ef\u6668\u8bfb\u8425_admin_src_tests_helpers_mock_helpers_ts", "target": "helpers_mock_helpers_mockapiget", "relation": "contains", "confidence": "EXTRACTED", "source_file": "/Users/lion/Nutstore Files/\u6211\u7684\u575a\u679c\u4e91/flylion/AI\u9879\u76ee\u5f00\u53d1/\u4e03\u4e2a\u4e60\u60ef\u6668\u8bfb\u8425/admin/src/tests/helpers/mock-helpers.ts", "source_location": "L59", "weight": 1.0}, {"source": "users_lion_nutstore_files_\u6211\u7684\u575a\u679c\u4e91_flylion_ai\u9879\u76ee\u5f00\u53d1_\u4e03\u4e2a\u4e60\u60ef\u6668\u8bfb\u8425_admin_src_tests_helpers_mock_helpers_ts", "target": "helpers_mock_helpers_mockapipost", "relation": "contains", "confidence": "EXTRACTED", "source_file": "/Users/lion/Nutstore Files/\u6211\u7684\u575a\u679c\u4e91/flylion/AI\u9879\u76ee\u5f00\u53d1/\u4e03\u4e2a\u4e60\u60ef\u6668\u8bfb\u8425/admin/src/tests/helpers/mock-helpers.ts", "source_location": "L66", "weight": 1.0}, {"source": "users_lion_nutstore_files_\u6211\u7684\u575a\u679c\u4e91_flylion_ai\u9879\u76ee\u5f00\u53d1_\u4e03\u4e2a\u4e60\u60ef\u6668\u8bfb\u8425_admin_src_tests_helpers_mock_helpers_ts", "target": "helpers_mock_helpers_mockapiput", "relation": "contains", "confidence": "EXTRACTED", "source_file": "/Users/lion/Nutstore Files/\u6211\u7684\u575a\u679c\u4e91/flylion/AI\u9879\u76ee\u5f00\u53d1/\u4e03\u4e2a\u4e60\u60ef\u6668\u8bfb\u8425/admin/src/tests/helpers/mock-helpers.ts", "source_location": "L73", "weight": 1.0}, {"source": "users_lion_nutstore_files_\u6211\u7684\u575a\u679c\u4e91_flylion_ai\u9879\u76ee\u5f00\u53d1_\u4e03\u4e2a\u4e60\u60ef\u6668\u8bfb\u8425_admin_src_tests_helpers_mock_helpers_ts", "target": "helpers_mock_helpers_mockapipatch", "relation": "contains", "confidence": "EXTRACTED", "source_file": "/Users/lion/Nutstore Files/\u6211\u7684\u575a\u679c\u4e91/flylion/AI\u9879\u76ee\u5f00\u53d1/\u4e03\u4e2a\u4e60\u60ef\u6668\u8bfb\u8425/admin/src/tests/helpers/mock-helpers.ts", "source_location": "L80", "weight": 1.0}, {"source": "users_lion_nutstore_files_\u6211\u7684\u575a\u679c\u4e91_flylion_ai\u9879\u76ee\u5f00\u53d1_\u4e03\u4e2a\u4e60\u60ef\u6668\u8bfb\u8425_admin_src_tests_helpers_mock_helpers_ts", "target": "helpers_mock_helpers_mockapidelete", "relation": "contains", "confidence": "EXTRACTED", "source_file": "/Users/lion/Nutstore Files/\u6211\u7684\u575a\u679c\u4e91/flylion/AI\u9879\u76ee\u5f00\u53d1/\u4e03\u4e2a\u4e60\u60ef\u6668\u8bfb\u8425/admin/src/tests/helpers/mock-helpers.ts", "source_location": "L87", "weight": 1.0}, {"source": "users_lion_nutstore_files_\u6211\u7684\u575a\u679c\u4e91_flylion_ai\u9879\u76ee\u5f00\u53d1_\u4e03\u4e2a\u4e60\u60ef\u6668\u8bfb\u8425_admin_src_tests_helpers_mock_helpers_ts", "target": "helpers_mock_helpers_mockapifailure", "relation": "contains", "confidence": "EXTRACTED", "source_file": "/Users/lion/Nutstore Files/\u6211\u7684\u575a\u679c\u4e91/flylion/AI\u9879\u76ee\u5f00\u53d1/\u4e03\u4e2a\u4e60\u60ef\u6668\u8bfb\u8425/admin/src/tests/helpers/mock-helpers.ts", "source_location": "L94", "weight": 1.0}, {"source": "users_lion_nutstore_files_\u6211\u7684\u575a\u679c\u4e91_flylion_ai\u9879\u76ee\u5f00\u53d1_\u4e03\u4e2a\u4e60\u60ef\u6668\u8bfb\u8425_admin_src_tests_helpers_mock_helpers_ts", "target": "helpers_mock_helpers_createmockstoregetter", "relation": "contains", "confidence": "EXTRACTED", "source_file": "/Users/lion/Nutstore Files/\u6211\u7684\u575a\u679c\u4e91/flylion/AI\u9879\u76ee\u5f00\u53d1/\u4e03\u4e2a\u4e60\u60ef\u6668\u8bfb\u8425/admin/src/tests/helpers/mock-helpers.ts", "source_location": "L105", "weight": 1.0}, {"source": "users_lion_nutstore_files_\u6211\u7684\u575a\u679c\u4e91_flylion_ai\u9879\u76ee\u5f00\u53d1_\u4e03\u4e2a\u4e60\u60ef\u6668\u8bfb\u8425_admin_src_tests_helpers_mock_helpers_ts", "target": "helpers_mock_helpers_createmockstoreaction", "relation": "contains", "confidence": "EXTRACTED", "source_file": "/Users/lion/Nutstore Files/\u6211\u7684\u575a\u679c\u4e91/flylion/AI\u9879\u76ee\u5f00\u53d1/\u4e03\u4e2a\u4e60\u60ef\u6668\u8bfb\u8425/admin/src/tests/helpers/mock-helpers.ts", "source_location": "L112", "weight": 1.0}, {"source": "users_lion_nutstore_files_\u6211\u7684\u575a\u679c\u4e91_flylion_ai\u9879\u76ee\u5f00\u53d1_\u4e03\u4e2a\u4e60\u60ef\u6668\u8bfb\u8425_admin_src_tests_helpers_mock_helpers_ts", "target": "helpers_mock_helpers_createmockstoremutation", "relation": "contains", "confidence": "EXTRACTED", "source_file": "/Users/lion/Nutstore Files/\u6211\u7684\u575a\u679c\u4e91/flylion/AI\u9879\u76ee\u5f00\u53d1/\u4e03\u4e2a\u4e60\u60ef\u6668\u8bfb\u8425/admin/src/tests/helpers/mock-helpers.ts", "source_location": "L119", "weight": 1.0}, {"source": "users_lion_nutstore_files_\u6211\u7684\u575a\u679c\u4e91_flylion_ai\u9879\u76ee\u5f00\u53d1_\u4e03\u4e2a\u4e60\u60ef\u6668\u8bfb\u8425_admin_src_tests_helpers_mock_helpers_ts", "target": "helpers_mock_helpers_createmockstore", "relation": "contains", "confidence": "EXTRACTED", "source_file": "/Users/lion/Nutstore Files/\u6211\u7684\u575a\u679c\u4e91/flylion/AI\u9879\u76ee\u5f00\u53d1/\u4e03\u4e2a\u4e60\u60ef\u6668\u8bfb\u8425/admin/src/tests/helpers/mock-helpers.ts", "source_location": "L126", "weight": 1.0}, {"source": "users_lion_nutstore_files_\u6211\u7684\u575a\u679c\u4e91_flylion_ai\u9879\u76ee\u5f00\u53d1_\u4e03\u4e2a\u4e60\u60ef\u6668\u8bfb\u8425_admin_src_tests_helpers_mock_helpers_ts", "target": "helpers_mock_helpers_createmockrouter", "relation": "contains", "confidence": "EXTRACTED", "source_file": "/Users/lion/Nutstore Files/\u6211\u7684\u575a\u679c\u4e91/flylion/AI\u9879\u76ee\u5f00\u53d1/\u4e03\u4e2a\u4e60\u60ef\u6668\u8bfb\u8425/admin/src/tests/helpers/mock-helpers.ts", "source_location": "L138", "weight": 1.0}, {"source": "users_lion_nutstore_files_\u6211\u7684\u575a\u679c\u4e91_flylion_ai\u9879\u76ee\u5f00\u53d1_\u4e03\u4e2a\u4e60\u60ef\u6668\u8bfb\u8425_admin_src_tests_helpers_mock_helpers_ts", "target": "helpers_mock_helpers_createmockrouteparams", "relation": "contains", "confidence": "EXTRACTED", "source_file": "/Users/lion/Nutstore Files/\u6211\u7684\u575a\u679c\u4e91/flylion/AI\u9879\u76ee\u5f00\u53d1/\u4e03\u4e2a\u4e60\u60ef\u6668\u8bfb\u8425/admin/src/tests/helpers/mock-helpers.ts", "source_location": "L151", "weight": 1.0}, {"source": "users_lion_nutstore_files_\u6211\u7684\u575a\u679c\u4e91_flylion_ai\u9879\u76ee\u5f00\u53d1_\u4e03\u4e2a\u4e60\u60ef\u6668\u8bfb\u8425_admin_src_tests_helpers_mock_helpers_ts", "target": "helpers_mock_helpers_createmocklocalstorage", "relation": "contains", "confidence": "EXTRACTED", "source_file": "/Users/lion/Nutstore Files/\u6211\u7684\u575a\u679c\u4e91/flylion/AI\u9879\u76ee\u5f00\u53d1/\u4e03\u4e2a\u4e60\u60ef\u6668\u8bfb\u8425/admin/src/tests/helpers/mock-helpers.ts", "source_location": "L163", "weight": 1.0}, {"source": "users_lion_nutstore_files_\u6211\u7684\u575a\u679c\u4e91_flylion_ai\u9879\u76ee\u5f00\u53d1_\u4e03\u4e2a\u4e60\u60ef\u6668\u8bfb\u8425_admin_src_tests_helpers_mock_helpers_ts", "target": "helpers_mock_helpers_createmocksessionstorage", "relation": "contains", "confidence": "EXTRACTED", "source_file": "/Users/lion/Nutstore Files/\u6211\u7684\u575a\u679c\u4e91/flylion/AI\u9879\u76ee\u5f00\u53d1/\u4e03\u4e2a\u4e60\u60ef\u6668\u8bfb\u8425/admin/src/tests/helpers/mock-helpers.ts", "source_location": "L198", "weight": 1.0}, {"source": "users_lion_nutstore_files_\u6211\u7684\u575a\u679c\u4e91_flylion_ai\u9879\u76ee\u5f00\u53d1_\u4e03\u4e2a\u4e60\u60ef\u6668\u8bfb\u8425_admin_src_tests_helpers_mock_helpers_ts", "target": "helpers_mock_helpers_mockwindowalert", "relation": "contains", "confidence": "EXTRACTED", "source_file": "/Users/lion/Nutstore Files/\u6211\u7684\u575a\u679c\u4e91/flylion/AI\u9879\u76ee\u5f00\u53d1/\u4e03\u4e2a\u4e60\u60ef\u6668\u8bfb\u8425/admin/src/tests/helpers/mock-helpers.ts", "source_location": "L233", "weight": 1.0}, {"source": "users_lion_nutstore_files_\u6211\u7684\u575a\u679c\u4e91_flylion_ai\u9879\u76ee\u5f00\u53d1_\u4e03\u4e2a\u4e60\u60ef\u6668\u8bfb\u8425_admin_src_tests_helpers_mock_helpers_ts", "target": "helpers_mock_helpers_mockconsolelog", "relation": "contains", "confidence": "EXTRACTED", "source_file": "/Users/lion/Nutstore Files/\u6211\u7684\u575a\u679c\u4e91/flylion/AI\u9879\u76ee\u5f00\u53d1/\u4e03\u4e2a\u4e60\u60ef\u6668\u8bfb\u8425/admin/src/tests/helpers/mock-helpers.ts", "source_location": "L242", "weight": 1.0}, {"source": "users_lion_nutstore_files_\u6211\u7684\u575a\u679c\u4e91_flylion_ai\u9879\u76ee\u5f00\u53d1_\u4e03\u4e2a\u4e60\u60ef\u6668\u8bfb\u8425_admin_src_tests_helpers_mock_helpers_ts", "target": "helpers_mock_helpers_mockconsoleerror", "relation": "contains", "confidence": "EXTRACTED", "source_file": "/Users/lion/Nutstore Files/\u6211\u7684\u575a\u679c\u4e91/flylion/AI\u9879\u76ee\u5f00\u53d1/\u4e03\u4e2a\u4e60\u60ef\u6668\u8bfb\u8425/admin/src/tests/helpers/mock-helpers.ts", "source_location": "L246", "weight": 1.0}, {"source": "users_lion_nutstore_files_\u6211\u7684\u575a\u679c\u4e91_flylion_ai\u9879\u76ee\u5f00\u53d1_\u4e03\u4e2a\u4e60\u60ef\u6668\u8bfb\u8425_admin_src_tests_helpers_mock_helpers_ts", "target": "helpers_mock_helpers_mockconsolewarn", "relation": "contains", "confidence": "EXTRACTED", "source_file": "/Users/lion/Nutstore Files/\u6211\u7684\u575a\u679c\u4e91/flylion/AI\u9879\u76ee\u5f00\u53d1/\u4e03\u4e2a\u4e60\u60ef\u6668\u8bfb\u8425/admin/src/tests/helpers/mock-helpers.ts", "source_location": "L250", "weight": 1.0}, {"source": "users_lion_nutstore_files_\u6211\u7684\u575a\u679c\u4e91_flylion_ai\u9879\u76ee\u5f00\u53d1_\u4e03\u4e2a\u4e60\u60ef\u6668\u8bfb\u8425_admin_src_tests_helpers_mock_helpers_ts", "target": "helpers_mock_helpers_waitfor", "relation": "contains", "confidence": "EXTRACTED", "source_file": "/Users/lion/Nutstore Files/\u6211\u7684\u575a\u679c\u4e91/flylion/AI\u9879\u76ee\u5f00\u53d1/\u4e03\u4e2a\u4e60\u60ef\u6668\u8bfb\u8425/admin/src/tests/helpers/mock-helpers.ts", "source_location": "L257", "weight": 1.0}, {"source": "users_lion_nutstore_files_\u6211\u7684\u575a\u679c\u4e91_flylion_ai\u9879\u76ee\u5f00\u53d1_\u4e03\u4e2a\u4e60\u60ef\u6668\u8bfb\u8425_admin_src_tests_helpers_mock_helpers_ts", "target": "helpers_mock_helpers_delay", "relation": "contains", "confidence": "EXTRACTED", "source_file": "/Users/lion/Nutstore Files/\u6211\u7684\u575a\u679c\u4e91/flylion/AI\u9879\u76ee\u5f00\u53d1/\u4e03\u4e2a\u4e60\u60ef\u6668\u8bfb\u8425/admin/src/tests/helpers/mock-helpers.ts", "source_location": "L276", "weight": 1.0}, {"source": "users_lion_nutstore_files_\u6211\u7684\u575a\u679c\u4e91_flylion_ai\u9879\u76ee\u5f00\u53d1_\u4e03\u4e2a\u4e60\u60ef\u6668\u8bfb\u8425_admin_src_tests_helpers_mock_helpers_ts", "target": "helpers_mock_helpers_createmockhttpinterceptor", "relation": "contains", "confidence": "EXTRACTED", "source_file": "/Users/lion/Nutstore Files/\u6211\u7684\u575a\u679c\u4e91/flylion/AI\u9879\u76ee\u5f00\u53d1/\u4e03\u4e2a\u4e60\u60ef\u6668\u8bfb\u8425/admin/src/tests/helpers/mock-helpers.ts", "source_location": "L283", "weight": 1.0}, {"source": "users_lion_nutstore_files_\u6211\u7684\u575a\u679c\u4e91_flylion_ai\u9879\u76ee\u5f00\u53d1_\u4e03\u4e2a\u4e60\u60ef\u6668\u8bfb\u8425_admin_src_tests_helpers_mock_helpers_ts", "target": "helpers_mock_helpers_resetallmocks", "relation": "contains", "confidence": "EXTRACTED", "source_file": "/Users/lion/Nutstore Files/\u6211\u7684\u575a\u679c\u4e91/flylion/AI\u9879\u76ee\u5f00\u53d1/\u4e03\u4e2a\u4e60\u60ef\u6668\u8bfb\u8425/admin/src/tests/helpers/mock-helpers.ts", "source_location": "L297", "weight": 1.0}, {"source": "users_lion_nutstore_files_\u6211\u7684\u575a\u679c\u4e91_flylion_ai\u9879\u76ee\u5f00\u53d1_\u4e03\u4e2a\u4e60\u60ef\u6668\u8bfb\u8425_admin_src_tests_helpers_mock_helpers_ts", "target": "helpers_mock_helpers_restoreallmocks", "relation": "contains", "confidence": "EXTRACTED", "source_file": "/Users/lion/Nutstore Files/\u6211\u7684\u575a\u679c\u4e91/flylion/AI\u9879\u76ee\u5f00\u53d1/\u4e03\u4e2a\u4e60\u60ef\u6668\u8bfb\u8425/admin/src/tests/helpers/mock-helpers.ts", "source_location": "L304", "weight": 1.0}, {"source": "helpers_mock_helpers_mockapifailure", "target": "helpers_mock_helpers_createmockapierror", "relation": "calls", "context": "call", "confidence": "EXTRACTED", "source_file": "/Users/lion/Nutstore Files/\u6211\u7684\u575a\u679c\u4e91/flylion/AI\u9879\u76ee\u5f00\u53d1/\u4e03\u4e2a\u4e60\u60ef\u6668\u8bfb\u8425/admin/src/tests/helpers/mock-helpers.ts", "source_location": "L96", "weight": 1.0}], "raw_calls": [{"caller_nid": "helpers_mock_helpers_createmockresponse", "callee": "fn", "is_member_call": true, "source_file": "/Users/lion/Nutstore Files/\u6211\u7684\u575a\u679c\u4e91/flylion/AI\u9879\u76ee\u5f00\u53d1/\u4e03\u4e2a\u4e60\u60ef\u6668\u8bfb\u8425/admin/src/tests/helpers/mock-helpers.ts", "source_location": "L17"}, {"caller_nid": "helpers_mock_helpers_createmockresponse", "callee": "fn", "is_member_call": true, "source_file": "/Users/lion/Nutstore Files/\u6211\u7684\u575a\u679c\u4e91/flylion/AI\u9879\u76ee\u5f00\u53d1/\u4e03\u4e2a\u4e60\u60ef\u6668\u8bfb\u8425/admin/src/tests/helpers/mock-helpers.ts", "source_location": "L21"}, {"caller_nid": "helpers_mock_helpers_createmockresponse", "callee": "fn", "is_member_call": true, "source_file": "/Users/lion/Nutstore Files/\u6211\u7684\u575a\u679c\u4e91/flylion/AI\u9879\u76ee\u5f00\u53d1/\u4e03\u4e2a\u4e60\u60ef\u6668\u8bfb\u8425/admin/src/tests/helpers/mock-helpers.ts", "source_location": "L25"}, {"caller_nid": "helpers_mock_helpers_createmockresponse", "callee": "bind", "is_member_call": true, "source_file": "/Users/lion/Nutstore Files/\u6211\u7684\u575a\u679c\u4e91/flylion/AI\u9879\u76ee\u5f00\u53d1/\u4e03\u4e2a\u4e60\u60ef\u6668\u8bfb\u8425/admin/src/tests/helpers/mock-helpers.ts", "source_location": "L31"}, {"caller_nid": "helpers_mock_helpers_createmockresponse", "callee": "bind", "is_member_call": true, "source_file": "/Users/lion/Nutstore Files/\u6211\u7684\u575a\u679c\u4e91/flylion/AI\u9879\u76ee\u5f00\u53d1/\u4e03\u4e2a\u4e60\u60ef\u6668\u8bfb\u8425/admin/src/tests/helpers/mock-helpers.ts", "source_location": "L32"}, {"caller_nid": "helpers_mock_helpers_createmockresponse", "callee": "bind", "is_member_call": true, "source_file": "/Users/lion/Nutstore Files/\u6211\u7684\u575a\u679c\u4e91/flylion/AI\u9879\u76ee\u5f00\u53d1/\u4e03\u4e2a\u4e60\u60ef\u6668\u8bfb\u8425/admin/src/tests/helpers/mock-helpers.ts", "source_location": "L33"}, {"caller_nid": "helpers_mock_helpers_mockapiget", "callee": "fn", "is_member_call": true, "source_file": "/Users/lion/Nutstore Files/\u6211\u7684\u575a\u679c\u4e91/flylion/AI\u9879\u76ee\u5f00\u53d1/\u4e03\u4e2a\u4e60\u60ef\u6668\u8bfb\u8425/admin/src/tests/helpers/mock-helpers.ts", "source_location": "L60"}, {"caller_nid": "helpers_mock_helpers_mockapipost", "callee": "fn", "is_member_call": true, "source_file": "/Users/lion/Nutstore Files/\u6211\u7684\u575a\u679c\u4e91/flylion/AI\u9879\u76ee\u5f00\u53d1/\u4e03\u4e2a\u4e60\u60ef\u6668\u8bfb\u8425/admin/src/tests/helpers/mock-helpers.ts", "source_location": "L67"}, {"caller_nid": "helpers_mock_helpers_mockapiput", "callee": "fn", "is_member_call": true, "source_file": "/Users/lion/Nutstore Files/\u6211\u7684\u575a\u679c\u4e91/flylion/AI\u9879\u76ee\u5f00\u53d1/\u4e03\u4e2a\u4e60\u60ef\u6668\u8bfb\u8425/admin/src/tests/helpers/mock-helpers.ts", "source_location": "L74"}, {"caller_nid": "helpers_mock_helpers_mockapipatch", "callee": "fn", "is_member_call": true, "source_file": "/Users/lion/Nutstore Files/\u6211\u7684\u575a\u679c\u4e91/flylion/AI\u9879\u76ee\u5f00\u53d1/\u4e03\u4e2a\u4e60\u60ef\u6668\u8bfb\u8425/admin/src/tests/helpers/mock-helpers.ts", "source_location": "L81"}, {"caller_nid": "helpers_mock_helpers_mockapidelete", "callee": "fn", "is_member_call": true, "source_file": "/Users/lion/Nutstore Files/\u6211\u7684\u575a\u679c\u4e91/flylion/AI\u9879\u76ee\u5f00\u53d1/\u4e03\u4e2a\u4e60\u60ef\u6668\u8bfb\u8425/admin/src/tests/helpers/mock-helpers.ts", "source_location": "L88"}, {"caller_nid": "helpers_mock_helpers_mockapifailure", "callee": "fn", "is_member_call": true, "source_file": "/Users/lion/Nutstore Files/\u6211\u7684\u575a\u679c\u4e91/flylion/AI\u9879\u76ee\u5f00\u53d1/\u4e03\u4e2a\u4e60\u60ef\u6668\u8bfb\u8425/admin/src/tests/helpers/mock-helpers.ts", "source_location": "L97"}, {"caller_nid": "helpers_mock_helpers_createmockstoregetter", "callee": "fn", "is_member_call": true, "source_file": "/Users/lion/Nutstore Files/\u6211\u7684\u575a\u679c\u4e91/flylion/AI\u9879\u76ee\u5f00\u53d1/\u4e03\u4e2a\u4e60\u60ef\u6668\u8bfb\u8425/admin/src/tests/helpers/mock-helpers.ts", "source_location": "L106"}, {"caller_nid": "helpers_mock_helpers_createmockstoreaction", "callee": "fn", "is_member_call": true, "source_file": "/Users/lion/Nutstore Files/\u6211\u7684\u575a\u679c\u4e91/flylion/AI\u9879\u76ee\u5f00\u53d1/\u4e03\u4e2a\u4e60\u60ef\u6668\u8bfb\u8425/admin/src/tests/helpers/mock-helpers.ts", "source_location": "L113"}, {"caller_nid": "helpers_mock_helpers_createmockstoremutation", "callee": "fn", "is_member_call": true, "source_file": "/Users/lion/Nutstore Files/\u6211\u7684\u575a\u679c\u4e91/flylion/AI\u9879\u76ee\u5f00\u53d1/\u4e03\u4e2a\u4e60\u60ef\u6668\u8bfb\u8425/admin/src/tests/helpers/mock-helpers.ts", "source_location": "L120"}, {"caller_nid": "helpers_mock_helpers_createmockstore", "callee": "fn", "is_member_call": true, "source_file": "/Users/lion/Nutstore Files/\u6211\u7684\u575a\u679c\u4e91/flylion/AI\u9879\u76ee\u5f00\u53d1/\u4e03\u4e2a\u4e60\u60ef\u6668\u8bfb\u8425/admin/src/tests/helpers/mock-helpers.ts", "source_location": "L128"}, {"caller_nid": "helpers_mock_helpers_createmockrouter", "callee": "fn", "is_member_call": true, "source_file": "/Users/lion/Nutstore Files/\u6211\u7684\u575a\u679c\u4e91/flylion/AI\u9879\u76ee\u5f00\u53d1/\u4e03\u4e2a\u4e60\u60ef\u6668\u8bfb\u8425/admin/src/tests/helpers/mock-helpers.ts", "source_location": "L139"}, {"caller_nid": "helpers_mock_helpers_createmockrouter", "callee": "fn", "is_member_call": true, "source_file": "/Users/lion/Nutstore Files/\u6211\u7684\u575a\u679c\u4e91/flylion/AI\u9879\u76ee\u5f00\u53d1/\u4e03\u4e2a\u4e60\u60ef\u6668\u8bfb\u8425/admin/src/tests/helpers/mock-helpers.ts", "source_location": "L140"}, {"caller_nid": "helpers_mock_helpers_createmockrouter", "callee": "fn", "is_member_call": true, "source_file": "/Users/lion/Nutstore Files/\u6211\u7684\u575a\u679c\u4e91/flylion/AI\u9879\u76ee\u5f00\u53d1/\u4e03\u4e2a\u4e60\u60ef\u6668\u8bfb\u8425/admin/src/tests/helpers/mock-helpers.ts", "source_location": "L141"}, {"caller_nid": "helpers_mock_helpers_createmockrouter", "callee": "fn", "is_member_call": true, "source_file": "/Users/lion/Nutstore Files/\u6211\u7684\u575a\u679c\u4e91/flylion/AI\u9879\u76ee\u5f00\u53d1/\u4e03\u4e2a\u4e60\u60ef\u6668\u8bfb\u8425/admin/src/tests/helpers/mock-helpers.ts", "source_location": "L142"}, {"caller_nid": "helpers_mock_helpers_createmockrouter", "callee": "fn", "is_member_call": true, "source_file": "/Users/lion/Nutstore Files/\u6211\u7684\u575a\u679c\u4e91/flylion/AI\u9879\u76ee\u5f00\u53d1/\u4e03\u4e2a\u4e60\u60ef\u6668\u8bfb\u8425/admin/src/tests/helpers/mock-helpers.ts", "source_location": "L143"}, {"caller_nid": "helpers_mock_helpers_mockwindowalert", "callee": "fn", "is_member_call": true, "source_file": "/Users/lion/Nutstore Files/\u6211\u7684\u575a\u679c\u4e91/flylion/AI\u9879\u76ee\u5f00\u53d1/\u4e03\u4e2a\u4e60\u60ef\u6668\u8bfb\u8425/admin/src/tests/helpers/mock-helpers.ts", "source_location": "L234"}, {"caller_nid": "helpers_mock_helpers_mockconsolelog", "callee": "mockImplementation", "is_member_call": true, "source_file": "/Users/lion/Nutstore Files/\u6211\u7684\u575a\u679c\u4e91/flylion/AI\u9879\u76ee\u5f00\u53d1/\u4e03\u4e2a\u4e60\u60ef\u6668\u8bfb\u8425/admin/src/tests/helpers/mock-helpers.ts", "source_location": "L243"}, {"caller_nid": "helpers_mock_helpers_mockconsolelog", "callee": "spyOn", "is_member_call": true, "source_file": "/Users/lion/Nutstore Files/\u6211\u7684\u575a\u679c\u4e91/flylion/AI\u9879\u76ee\u5f00\u53d1/\u4e03\u4e2a\u4e60\u60ef\u6668\u8bfb\u8425/admin/src/tests/helpers/mock-helpers.ts", "source_location": "L243"}, {"caller_nid": "helpers_mock_helpers_mockconsoleerror", "callee": "mockImplementation", "is_member_call": true, "source_file": "/Users/lion/Nutstore Files/\u6211\u7684\u575a\u679c\u4e91/flylion/AI\u9879\u76ee\u5f00\u53d1/\u4e03\u4e2a\u4e60\u60ef\u6668\u8bfb\u8425/admin/src/tests/helpers/mock-helpers.ts", "source_location": "L247"}, {"caller_nid": "helpers_mock_helpers_mockconsoleerror", "callee": "spyOn", "is_member_call": true, "source_file": "/Users/lion/Nutstore Files/\u6211\u7684\u575a\u679c\u4e91/flylion/AI\u9879\u76ee\u5f00\u53d1/\u4e03\u4e2a\u4e60\u60ef\u6668\u8bfb\u8425/admin/src/tests/helpers/mock-helpers.ts", "source_location": "L247"}, {"caller_nid": "helpers_mock_helpers_mockconsolewarn", "callee": "mockImplementation", "is_member_call": true, "source_file": "/Users/lion/Nutstore Files/\u6211\u7684\u575a\u679c\u4e91/flylion/AI\u9879\u76ee\u5f00\u53d1/\u4e03\u4e2a\u4e60\u60ef\u6668\u8bfb\u8425/admin/src/tests/helpers/mock-helpers.ts", "source_location": "L251"}, {"caller_nid": "helpers_mock_helpers_mockconsolewarn", "callee": "spyOn", "is_member_call": true, "source_file": "/Users/lion/Nutstore Files/\u6211\u7684\u575a\u679c\u4e91/flylion/AI\u9879\u76ee\u5f00\u53d1/\u4e03\u4e2a\u4e60\u60ef\u6668\u8bfb\u8425/admin/src/tests/helpers/mock-helpers.ts", "source_location": "L251"}, {"caller_nid": "helpers_mock_helpers_createmockhttpinterceptor", "callee": "fn", "is_member_call": true, "source_file": "/Users/lion/Nutstore Files/\u6211\u7684\u575a\u679c\u4e91/flylion/AI\u9879\u76ee\u5f00\u53d1/\u4e03\u4e2a\u4e60\u60ef\u6668\u8bfb\u8425/admin/src/tests/helpers/mock-helpers.ts", "source_location": "L285"}, {"caller_nid": "helpers_mock_helpers_createmockhttpinterceptor", "callee": "fn", "is_member_call": true, "source_file": "/Users/lion/Nutstore Files/\u6211\u7684\u575a\u679c\u4e91/flylion/AI\u9879\u76ee\u5f00\u53d1/\u4e03\u4e2a\u4e60\u60ef\u6668\u8bfb\u8425/admin/src/tests/helpers/mock-helpers.ts", "source_location": "L286"}, {"caller_nid": "helpers_mock_helpers_createmockhttpinterceptor", "callee": "fn", "is_member_call": true, "source_file": "/Users/lion/Nutstore Files/\u6211\u7684\u575a\u679c\u4e91/flylion/AI\u9879\u76ee\u5f00\u53d1/\u4e03\u4e2a\u4e60\u60ef\u6668\u8bfb\u8425/admin/src/tests/helpers/mock-helpers.ts", "source_location": "L289"}, {"caller_nid": "helpers_mock_helpers_createmockhttpinterceptor", "callee": "fn", "is_member_call": true, "source_file": "/Users/lion/Nutstore Files/\u6211\u7684\u575a\u679c\u4e91/flylion/AI\u9879\u76ee\u5f00\u53d1/\u4e03\u4e2a\u4e60\u60ef\u6668\u8bfb\u8425/admin/src/tests/helpers/mock-helpers.ts", "source_location": "L290"}, {"caller_nid": "helpers_mock_helpers_resetallmocks", "callee": "clearAllMocks", "is_member_call": true, "source_file": "/Users/lion/Nutstore Files/\u6211\u7684\u575a\u679c\u4e91/flylion/AI\u9879\u76ee\u5f00\u53d1/\u4e03\u4e2a\u4e60\u60ef\u6668\u8bfb\u8425/admin/src/tests/helpers/mock-helpers.ts", "source_location": "L298"}]}