{"nodes": [{"id": "users_lion_nutstore_files_\u6211\u7684\u575a\u679c\u4e91_flylion_ai\u9879\u76ee\u5f00\u53d1_\u4e03\u4e2a\u4e60\u60ef\u6668\u8bfb\u8425_backend_src_utils_websocket_js", "label": "websocket.js", "file_type": "code", "source_file": "/Users/lion/Nutstore Files/\u6211\u7684\u575a\u679c\u4e91/flylion/AI\u9879\u76ee\u5f00\u53d1/\u4e03\u4e2a\u4e60\u60ef\u6668\u8bfb\u8425/backend/src/utils/websocket.js", "source_location": "L1"}, {"id": "utils_websocket_url", "label": "url", "file_type": "code", "source_file": "/Users/lion/Nutstore Files/\u6211\u7684\u575a\u679c\u4e91/flylion/AI\u9879\u76ee\u5f00\u53d1/\u4e03\u4e2a\u4e60\u60ef\u6668\u8bfb\u8425/backend/src/utils/websocket.js", "source_location": "L7"}, {"id": "utils_websocket_websocket", "label": "{ WebSocket }", "file_type": "code", "source_file": "/Users/lion/Nutstore Files/\u6211\u7684\u575a\u679c\u4e91/flylion/AI\u9879\u76ee\u5f00\u53d1/\u4e03\u4e2a\u4e60\u60ef\u6668\u8bfb\u8425/backend/src/utils/websocket.js", "source_location": "L8"}, {"id": "utils_websocket_verifyaccesstoken_consumewstoken", "label": "{ verifyAccessToken, consumeWsToken }", "file_type": "code", "source_file": "/Users/lion/Nutstore Files/\u6211\u7684\u575a\u679c\u4e91/flylion/AI\u9879\u76ee\u5f00\u53d1/\u4e03\u4e2a\u4e60\u60ef\u6668\u8bfb\u8425/backend/src/utils/websocket.js", "source_location": "L9"}, {"id": "utils_websocket_runwithtenant", "label": "{ runWithTenant }", "file_type": "code", "source_file": "/Users/lion/Nutstore Files/\u6211\u7684\u575a\u679c\u4e91/flylion/AI\u9879\u76ee\u5f00\u53d1/\u4e03\u4e2a\u4e60\u60ef\u6668\u8bfb\u8425/backend/src/utils/websocket.js", "source_location": "L10"}, {"id": "utils_websocket_logger", "label": "logger", "file_type": "code", "source_file": "/Users/lion/Nutstore Files/\u6211\u7684\u575a\u679c\u4e91/flylion/AI\u9879\u76ee\u5f00\u53d1/\u4e03\u4e2a\u4e60\u60ef\u6668\u8bfb\u8425/backend/src/utils/websocket.js", "source_location": "L11"}, {"id": "utils_websocket_websocketmanager", "label": "WebSocketManager", "file_type": "code", "source_file": "/Users/lion/Nutstore Files/\u6211\u7684\u575a\u679c\u4e91/flylion/AI\u9879\u76ee\u5f00\u53d1/\u4e03\u4e2a\u4e60\u60ef\u6668\u8bfb\u8425/backend/src/utils/websocket.js", "source_location": "L13"}, {"id": "utils_websocket_websocketmanager_constructor", "label": ".constructor()", "file_type": "code", "source_file": "/Users/lion/Nutstore Files/\u6211\u7684\u575a\u679c\u4e91/flylion/AI\u9879\u76ee\u5f00\u53d1/\u4e03\u4e2a\u4e60\u60ef\u6668\u8bfb\u8425/backend/src/utils/websocket.js", "source_location": "L14"}, {"id": "utils_websocket_websocketmanager_installauthandconnection", "label": "._installAuthAndConnection()", "file_type": "code", "source_file": "/Users/lion/Nutstore Files/\u6211\u7684\u575a\u679c\u4e91/flylion/AI\u9879\u76ee\u5f00\u53d1/\u4e03\u4e2a\u4e60\u60ef\u6668\u8bfb\u8425/backend/src/utils/websocket.js", "source_location": "L27"}, {"id": "utils_websocket_websocketmanager_send", "label": "._send()", "file_type": "code", "source_file": "/Users/lion/Nutstore Files/\u6211\u7684\u575a\u679c\u4e91/flylion/AI\u9879\u76ee\u5f00\u53d1/\u4e03\u4e2a\u4e60\u60ef\u6668\u8bfb\u8425/backend/src/utils/websocket.js", "source_location": "L78"}, {"id": "utils_websocket_websocketmanager_handlemessage", "label": "._handleMessage()", "file_type": "code", "source_file": "/Users/lion/Nutstore Files/\u6211\u7684\u575a\u679c\u4e91/flylion/AI\u9879\u76ee\u5f00\u53d1/\u4e03\u4e2a\u4e60\u60ef\u6668\u8bfb\u8425/backend/src/utils/websocket.js", "source_location": "L84"}, {"id": "utils_websocket_websocketmanager_handleclose", "label": "._handleClose()", "file_type": "code", "source_file": "/Users/lion/Nutstore Files/\u6211\u7684\u575a\u679c\u4e91/flylion/AI\u9879\u76ee\u5f00\u53d1/\u4e03\u4e2a\u4e60\u60ef\u6668\u8bfb\u8425/backend/src/utils/websocket.js", "source_location": "L107"}, {"id": "utils_websocket_websocketmanager_installheartbeat", "label": "._installHeartbeat()", "file_type": "code", "source_file": "/Users/lion/Nutstore Files/\u6211\u7684\u575a\u679c\u4e91/flylion/AI\u9879\u76ee\u5f00\u53d1/\u4e03\u4e2a\u4e60\u60ef\u6668\u8bfb\u8425/backend/src/utils/websocket.js", "source_location": "L125"}, {"id": "utils_websocket_websocketmanager_pushnotificationtouser", "label": ".pushNotificationToUser()", "file_type": "code", "source_file": "/Users/lion/Nutstore Files/\u6211\u7684\u575a\u679c\u4e91/flylion/AI\u9879\u76ee\u5f00\u53d1/\u4e03\u4e2a\u4e60\u60ef\u6668\u8bfb\u8425/backend/src/utils/websocket.js", "source_location": "L144"}, {"id": "utils_websocket_websocketmanager_pushnotificationtotenant", "label": ".pushNotificationToTenant()", "file_type": "code", "source_file": "/Users/lion/Nutstore Files/\u6211\u7684\u575a\u679c\u4e91/flylion/AI\u9879\u76ee\u5f00\u53d1/\u4e03\u4e2a\u4e60\u60ef\u6668\u8bfb\u8425/backend/src/utils/websocket.js", "source_location": "L155"}, {"id": "utils_websocket_websocketmanager_isuseronline", "label": ".isUserOnline()", "file_type": "code", "source_file": "/Users/lion/Nutstore Files/\u6211\u7684\u575a\u679c\u4e91/flylion/AI\u9879\u76ee\u5f00\u53d1/\u4e03\u4e2a\u4e60\u60ef\u6668\u8bfb\u8425/backend/src/utils/websocket.js", "source_location": "L166"}, {"id": "utils_websocket_websocketmanager_getusersocketcount", "label": ".getUserSocketCount()", "file_type": "code", "source_file": "/Users/lion/Nutstore Files/\u6211\u7684\u575a\u679c\u4e91/flylion/AI\u9879\u76ee\u5f00\u53d1/\u4e03\u4e2a\u4e60\u60ef\u6668\u8bfb\u8425/backend/src/utils/websocket.js", "source_location": "L171"}, {"id": "utils_websocket_websocketmanager_getonlineuserscount", "label": ".getOnlineUsersCount()", "file_type": "code", "source_file": "/Users/lion/Nutstore Files/\u6211\u7684\u575a\u679c\u4e91/flylion/AI\u9879\u76ee\u5f00\u53d1/\u4e03\u4e2a\u4e60\u60ef\u6668\u8bfb\u8425/backend/src/utils/websocket.js", "source_location": "L176"}, {"id": "utils_websocket_websocketmanager_getonlineusers", "label": ".getOnlineUsers()", "file_type": "code", "source_file": "/Users/lion/Nutstore Files/\u6211\u7684\u575a\u679c\u4e91/flylion/AI\u9879\u76ee\u5f00\u53d1/\u4e03\u4e2a\u4e60\u60ef\u6668\u8bfb\u8425/backend/src/utils/websocket.js", "source_location": "L180"}, {"id": "utils_websocket_websocketmanager_getstats", "label": ".getStats()", "file_type": "code", "source_file": "/Users/lion/Nutstore Files/\u6211\u7684\u575a\u679c\u4e91/flylion/AI\u9879\u76ee\u5f00\u53d1/\u4e03\u4e2a\u4e60\u60ef\u6668\u8bfb\u8425/backend/src/utils/websocket.js", "source_location": "L184"}, {"id": "utils_websocket_websocketmanager_publishtootherinstances", "label": "._publishToOtherInstances()", "file_type": "code", "source_file": "/Users/lion/Nutstore Files/\u6211\u7684\u575a\u679c\u4e91/flylion/AI\u9879\u76ee\u5f00\u53d1/\u4e03\u4e2a\u4e60\u60ef\u6668\u8bfb\u8425/backend/src/utils/websocket.js", "source_location": "L198"}, {"id": "utils_websocket_websocketmanager_setpubsub", "label": ".setPubSub()", "file_type": "code", "source_file": "/Users/lion/Nutstore Files/\u6211\u7684\u575a\u679c\u4e91/flylion/AI\u9879\u76ee\u5f00\u53d1/\u4e03\u4e2a\u4e60\u60ef\u6668\u8bfb\u8425/backend/src/utils/websocket.js", "source_location": "L201"}], "edges": [{"source": "users_lion_nutstore_files_\u6211\u7684\u575a\u679c\u4e91_flylion_ai\u9879\u76ee\u5f00\u53d1_\u4e03\u4e2a\u4e60\u60ef\u6668\u8bfb\u8425_backend_src_utils_websocket_js", "target": "url", "relation": "imports_from", "context": "import", "confidence": "EXTRACTED", "source_file": "/Users/lion/Nutstore Files/\u6211\u7684\u575a\u679c\u4e91/flylion/AI\u9879\u76ee\u5f00\u53d1/\u4e03\u4e2a\u4e60\u60ef\u6668\u8bfb\u8425/backend/src/utils/websocket.js", "source_location": "L7", "weight": 1.0}, {"source": "users_lion_nutstore_files_\u6211\u7684\u575a\u679c\u4e91_flylion_ai\u9879\u76ee\u5f00\u53d1_\u4e03\u4e2a\u4e60\u60ef\u6668\u8bfb\u8425_backend_src_utils_websocket_js", "target": "utils_websocket_url", "relation": "contains", "confidence": "EXTRACTED", "source_file": "/Users/lion/Nutstore Files/\u6211\u7684\u575a\u679c\u4e91/flylion/AI\u9879\u76ee\u5f00\u53d1/\u4e03\u4e2a\u4e60\u60ef\u6668\u8bfb\u8425/backend/src/utils/websocket.js", "source_location": "L7", "weight": 1.0}, {"source": "users_lion_nutstore_files_\u6211\u7684\u575a\u679c\u4e91_flylion_ai\u9879\u76ee\u5f00\u53d1_\u4e03\u4e2a\u4e60\u60ef\u6668\u8bfb\u8425_backend_src_utils_websocket_js", "target": "ws", "relation": "imports_from", "context": "import", "confidence": "EXTRACTED", "source_file": "/Users/lion/Nutstore Files/\u6211\u7684\u575a\u679c\u4e91/flylion/AI\u9879\u76ee\u5f00\u53d1/\u4e03\u4e2a\u4e60\u60ef\u6668\u8bfb\u8425/backend/src/utils/websocket.js", "source_location": "L8", "weight": 1.0}, {"source": "users_lion_nutstore_files_\u6211\u7684\u575a\u679c\u4e91_flylion_ai\u9879\u76ee\u5f00\u53d1_\u4e03\u4e2a\u4e60\u60ef\u6668\u8bfb\u8425_backend_src_utils_websocket_js", "target": "utils_websocket_websocket", "relation": "contains", "confidence": "EXTRACTED", "source_file": "/Users/lion/Nutstore Files/\u6211\u7684\u575a\u679c\u4e91/flylion/AI\u9879\u76ee\u5f00\u53d1/\u4e03\u4e2a\u4e60\u60ef\u6668\u8bfb\u8425/backend/src/utils/websocket.js", "source_location": "L8", "weight": 1.0}, {"source": "users_lion_nutstore_files_\u6211\u7684\u575a\u679c\u4e91_flylion_ai\u9879\u76ee\u5f00\u53d1_\u4e03\u4e2a\u4e60\u60ef\u6668\u8bfb\u8425_backend_src_utils_websocket_js", "target": "users_lion_nutstore_files_\u6211\u7684\u575a\u679c\u4e91_flylion_ai\u9879\u76ee\u5f00\u53d1_\u4e03\u4e2a\u4e60\u60ef\u6668\u8bfb\u8425_backend_src_utils_jwt_js", "relation": "imports_from", "context": "import", "confidence": "EXTRACTED", "source_file": "/Users/lion/Nutstore Files/\u6211\u7684\u575a\u679c\u4e91/flylion/AI\u9879\u76ee\u5f00\u53d1/\u4e03\u4e2a\u4e60\u60ef\u6668\u8bfb\u8425/backend/src/utils/websocket.js", "source_location": "L9", "weight": 1.0}, {"source": "users_lion_nutstore_files_\u6211\u7684\u575a\u679c\u4e91_flylion_ai\u9879\u76ee\u5f00\u53d1_\u4e03\u4e2a\u4e60\u60ef\u6668\u8bfb\u8425_backend_src_utils_websocket_js", "target": "utils_jwt_verifyaccesstoken", "relation": "imports", "context": "import", "confidence": "EXTRACTED", "source_file": "/Users/lion/Nutstore Files/\u6211\u7684\u575a\u679c\u4e91/flylion/AI\u9879\u76ee\u5f00\u53d1/\u4e03\u4e2a\u4e60\u60ef\u6668\u8bfb\u8425/backend/src/utils/websocket.js", "source_location": "L9", "weight": 1.0}, {"source": "users_lion_nutstore_files_\u6211\u7684\u575a\u679c\u4e91_flylion_ai\u9879\u76ee\u5f00\u53d1_\u4e03\u4e2a\u4e60\u60ef\u6668\u8bfb\u8425_backend_src_utils_websocket_js", "target": "utils_jwt_consumewstoken", "relation": "imports", "context": "import", "confidence": "EXTRACTED", "source_file": "/Users/lion/Nutstore Files/\u6211\u7684\u575a\u679c\u4e91/flylion/AI\u9879\u76ee\u5f00\u53d1/\u4e03\u4e2a\u4e60\u60ef\u6668\u8bfb\u8425/backend/src/utils/websocket.js", "source_location": "L9", "weight": 1.0}, {"source": "users_lion_nutstore_files_\u6211\u7684\u575a\u679c\u4e91_flylion_ai\u9879\u76ee\u5f00\u53d1_\u4e03\u4e2a\u4e60\u60ef\u6668\u8bfb\u8425_backend_src_utils_websocket_js", "target": "utils_websocket_verifyaccesstoken_consumewstoken", "relation": "contains", "confidence": "EXTRACTED", "source_file": "/Users/lion/Nutstore Files/\u6211\u7684\u575a\u679c\u4e91/flylion/AI\u9879\u76ee\u5f00\u53d1/\u4e03\u4e2a\u4e60\u60ef\u6668\u8bfb\u8425/backend/src/utils/websocket.js", "source_location": "L9", "weight": 1.0}, {"source": "users_lion_nutstore_files_\u6211\u7684\u575a\u679c\u4e91_flylion_ai\u9879\u76ee\u5f00\u53d1_\u4e03\u4e2a\u4e60\u60ef\u6668\u8bfb\u8425_backend_src_utils_websocket_js", "target": "users_lion_nutstore_files_\u6211\u7684\u575a\u679c\u4e91_flylion_ai\u9879\u76ee\u5f00\u53d1_\u4e03\u4e2a\u4e60\u60ef\u6668\u8bfb\u8425_backend_src_utils_tenantcontext_js", "relation": "imports_from", "context": "import", "confidence": "EXTRACTED", "source_file": "/Users/lion/Nutstore Files/\u6211\u7684\u575a\u679c\u4e91/flylion/AI\u9879\u76ee\u5f00\u53d1/\u4e03\u4e2a\u4e60\u60ef\u6668\u8bfb\u8425/backend/src/utils/websocket.js", "source_location": "L10", "weight": 1.0}, {"source": "users_lion_nutstore_files_\u6211\u7684\u575a\u679c\u4e91_flylion_ai\u9879\u76ee\u5f00\u53d1_\u4e03\u4e2a\u4e60\u60ef\u6668\u8bfb\u8425_backend_src_utils_websocket_js", "target": "utils_tenantcontext_runwithtenant", "relation": "imports", "context": "import", "confidence": "EXTRACTED", "source_file": "/Users/lion/Nutstore Files/\u6211\u7684\u575a\u679c\u4e91/flylion/AI\u9879\u76ee\u5f00\u53d1/\u4e03\u4e2a\u4e60\u60ef\u6668\u8bfb\u8425/backend/src/utils/websocket.js", "source_location": "L10", "weight": 1.0}, {"source": "users_lion_nutstore_files_\u6211\u7684\u575a\u679c\u4e91_flylion_ai\u9879\u76ee\u5f00\u53d1_\u4e03\u4e2a\u4e60\u60ef\u6668\u8bfb\u8425_backend_src_utils_websocket_js", "target": "utils_websocket_runwithtenant", "relation": "contains", "confidence": "EXTRACTED", "source_file": "/Users/lion/Nutstore Files/\u6211\u7684\u575a\u679c\u4e91/flylion/AI\u9879\u76ee\u5f00\u53d1/\u4e03\u4e2a\u4e60\u60ef\u6668\u8bfb\u8425/backend/src/utils/websocket.js", "source_location": "L10", "weight": 1.0}, {"source": "users_lion_nutstore_files_\u6211\u7684\u575a\u679c\u4e91_flylion_ai\u9879\u76ee\u5f00\u53d1_\u4e03\u4e2a\u4e60\u60ef\u6668\u8bfb\u8425_backend_src_utils_websocket_js", "target": "users_lion_nutstore_files_\u6211\u7684\u575a\u679c\u4e91_flylion_ai\u9879\u76ee\u5f00\u53d1_\u4e03\u4e2a\u4e60\u60ef\u6668\u8bfb\u8425_backend_src_utils_logger_js", "relation": "imports_from", "context": "import", "confidence": "EXTRACTED", "source_file": "/Users/lion/Nutstore Files/\u6211\u7684\u575a\u679c\u4e91/flylion/AI\u9879\u76ee\u5f00\u53d1/\u4e03\u4e2a\u4e60\u60ef\u6668\u8bfb\u8425/backend/src/utils/websocket.js", "source_location": "L11", "weight": 1.0}, {"source": "users_lion_nutstore_files_\u6211\u7684\u575a\u679c\u4e91_flylion_ai\u9879\u76ee\u5f00\u53d1_\u4e03\u4e2a\u4e60\u60ef\u6668\u8bfb\u8425_backend_src_utils_websocket_js", "target": "utils_websocket_logger", "relation": "contains", "confidence": "EXTRACTED", "source_file": "/Users/lion/Nutstore Files/\u6211\u7684\u575a\u679c\u4e91/flylion/AI\u9879\u76ee\u5f00\u53d1/\u4e03\u4e2a\u4e60\u60ef\u6668\u8bfb\u8425/backend/src/utils/websocket.js", "source_location": "L11", "weight": 1.0}, {"source": "users_lion_nutstore_files_\u6211\u7684\u575a\u679c\u4e91_flylion_ai\u9879\u76ee\u5f00\u53d1_\u4e03\u4e2a\u4e60\u60ef\u6668\u8bfb\u8425_backend_src_utils_websocket_js", "target": "utils_websocket_websocketmanager", "relation": "contains", "confidence": "EXTRACTED", "source_file": "/Users/lion/Nutstore Files/\u6211\u7684\u575a\u679c\u4e91/flylion/AI\u9879\u76ee\u5f00\u53d1/\u4e03\u4e2a\u4e60\u60ef\u6668\u8bfb\u8425/backend/src/utils/websocket.js", "source_location": "L13", "weight": 1.0}, {"source": "utils_websocket_websocketmanager", "target": "utils_websocket_websocketmanager_constructor", "relation": "method", "confidence": "EXTRACTED", "source_file": "/Users/lion/Nutstore Files/\u6211\u7684\u575a\u679c\u4e91/flylion/AI\u9879\u76ee\u5f00\u53d1/\u4e03\u4e2a\u4e60\u60ef\u6668\u8bfb\u8425/backend/src/utils/websocket.js", "source_location": "L14", "weight": 1.0}, {"source": "utils_websocket_websocketmanager", "target": "utils_websocket_websocketmanager_installauthandconnection", "relation": "method", "confidence": "EXTRACTED", "source_file": "/Users/lion/Nutstore Files/\u6211\u7684\u575a\u679c\u4e91/flylion/AI\u9879\u76ee\u5f00\u53d1/\u4e03\u4e2a\u4e60\u60ef\u6668\u8bfb\u8425/backend/src/utils/websocket.js", "source_location": "L27", "weight": 1.0}, {"source": "utils_websocket_websocketmanager", "target": "utils_websocket_websocketmanager_send", "relation": "method", "confidence": "EXTRACTED", "source_file": "/Users/lion/Nutstore Files/\u6211\u7684\u575a\u679c\u4e91/flylion/AI\u9879\u76ee\u5f00\u53d1/\u4e03\u4e2a\u4e60\u60ef\u6668\u8bfb\u8425/backend/src/utils/websocket.js", "source_location": "L78", "weight": 1.0}, {"source": "utils_websocket_websocketmanager", "target": "utils_websocket_websocketmanager_handlemessage", "relation": "method", "confidence": "EXTRACTED", "source_file": "/Users/lion/Nutstore Files/\u6211\u7684\u575a\u679c\u4e91/flylion/AI\u9879\u76ee\u5f00\u53d1/\u4e03\u4e2a\u4e60\u60ef\u6668\u8bfb\u8425/backend/src/utils/websocket.js", "source_location": "L84", "weight": 1.0}, {"source": "utils_websocket_websocketmanager", "target": "utils_websocket_websocketmanager_handleclose", "relation": "method", "confidence": "EXTRACTED", "source_file": "/Users/lion/Nutstore Files/\u6211\u7684\u575a\u679c\u4e91/flylion/AI\u9879\u76ee\u5f00\u53d1/\u4e03\u4e2a\u4e60\u60ef\u6668\u8bfb\u8425/backend/src/utils/websocket.js", "source_location": "L107", "weight": 1.0}, {"source": "utils_websocket_websocketmanager", "target": "utils_websocket_websocketmanager_installheartbeat", "relation": "method", "confidence": "EXTRACTED", "source_file": "/Users/lion/Nutstore Files/\u6211\u7684\u575a\u679c\u4e91/flylion/AI\u9879\u76ee\u5f00\u53d1/\u4e03\u4e2a\u4e60\u60ef\u6668\u8bfb\u8425/backend/src/utils/websocket.js", "source_location": "L125", "weight": 1.0}, {"source": "utils_websocket_websocketmanager", "target": "utils_websocket_websocketmanager_pushnotificationtouser", "relation": "method", "confidence": "EXTRACTED", "source_file": "/Users/lion/Nutstore Files/\u6211\u7684\u575a\u679c\u4e91/flylion/AI\u9879\u76ee\u5f00\u53d1/\u4e03\u4e2a\u4e60\u60ef\u6668\u8bfb\u8425/backend/src/utils/websocket.js", "source_location": "L144", "weight": 1.0}, {"source": "utils_websocket_websocketmanager", "target": "utils_websocket_websocketmanager_pushnotificationtotenant", "relation": "method", "confidence": "EXTRACTED", "source_file": "/Users/lion/Nutstore Files/\u6211\u7684\u575a\u679c\u4e91/flylion/AI\u9879\u76ee\u5f00\u53d1/\u4e03\u4e2a\u4e60\u60ef\u6668\u8bfb\u8425/backend/src/utils/websocket.js", "source_location": "L155", "weight": 1.0}, {"source": "utils_websocket_websocketmanager", "target": "utils_websocket_websocketmanager_isuseronline", "relation": "method", "confidence": "EXTRACTED", "source_file": "/Users/lion/Nutstore Files/\u6211\u7684\u575a\u679c\u4e91/flylion/AI\u9879\u76ee\u5f00\u53d1/\u4e03\u4e2a\u4e60\u60ef\u6668\u8bfb\u8425/backend/src/utils/websocket.js", "source_location": "L166", "weight": 1.0}, {"source": "utils_websocket_websocketmanager", "target": "utils_websocket_websocketmanager_getusersocketcount", "relation": "method", "confidence": "EXTRACTED", "source_file": "/Users/lion/Nutstore Files/\u6211\u7684\u575a\u679c\u4e91/flylion/AI\u9879\u76ee\u5f00\u53d1/\u4e03\u4e2a\u4e60\u60ef\u6668\u8bfb\u8425/backend/src/utils/websocket.js", "source_location": "L171", "weight": 1.0}, {"source": "utils_websocket_websocketmanager", "target": "utils_websocket_websocketmanager_getonlineuserscount", "relation": "method", "confidence": "EXTRACTED", "source_file": "/Users/lion/Nutstore Files/\u6211\u7684\u575a\u679c\u4e91/flylion/AI\u9879\u76ee\u5f00\u53d1/\u4e03\u4e2a\u4e60\u60ef\u6668\u8bfb\u8425/backend/src/utils/websocket.js", "source_location": "L176", "weight": 1.0}, {"source": "utils_websocket_websocketmanager", "target": "utils_websocket_websocketmanager_getonlineusers", "relation": "method", "confidence": "EXTRACTED", "source_file": "/Users/lion/Nutstore Files/\u6211\u7684\u575a\u679c\u4e91/flylion/AI\u9879\u76ee\u5f00\u53d1/\u4e03\u4e2a\u4e60\u60ef\u6668\u8bfb\u8425/backend/src/utils/websocket.js", "source_location": "L180", "weight": 1.0}, {"source": "utils_websocket_websocketmanager", "target": "utils_websocket_websocketmanager_getstats", "relation": "method", "confidence": "EXTRACTED", "source_file": "/Users/lion/Nutstore Files/\u6211\u7684\u575a\u679c\u4e91/flylion/AI\u9879\u76ee\u5f00\u53d1/\u4e03\u4e2a\u4e60\u60ef\u6668\u8bfb\u8425/backend/src/utils/websocket.js", "source_location": "L184", "weight": 1.0}, {"source": "utils_websocket_websocketmanager", "target": "utils_websocket_websocketmanager_publishtootherinstances", "relation": "method", "confidence": "EXTRACTED", "source_file": "/Users/lion/Nutstore Files/\u6211\u7684\u575a\u679c\u4e91/flylion/AI\u9879\u76ee\u5f00\u53d1/\u4e03\u4e2a\u4e60\u60ef\u6668\u8bfb\u8425/backend/src/utils/websocket.js", "source_location": "L198", "weight": 1.0}, {"source": "utils_websocket_websocketmanager", "target": "utils_websocket_websocketmanager_setpubsub", "relation": "method", "confidence": "EXTRACTED", "source_file": "/Users/lion/Nutstore Files/\u6211\u7684\u575a\u679c\u4e91/flylion/AI\u9879\u76ee\u5f00\u53d1/\u4e03\u4e2a\u4e60\u60ef\u6668\u8bfb\u8425/backend/src/utils/websocket.js", "source_location": "L201", "weight": 1.0}, {"source": "utils_websocket_websocketmanager_constructor", "target": "utils_websocket_websocketmanager_installauthandconnection", "relation": "calls", "context": "call", "confidence": "EXTRACTED", "source_file": "/Users/lion/Nutstore Files/\u6211\u7684\u575a\u679c\u4e91/flylion/AI\u9879\u76ee\u5f00\u53d1/\u4e03\u4e2a\u4e60\u60ef\u6668\u8bfb\u8425/backend/src/utils/websocket.js", "source_location": "L23", "weight": 1.0}, {"source": "utils_websocket_websocketmanager_constructor", "target": "utils_websocket_websocketmanager_installheartbeat", "relation": "calls", "context": "call", "confidence": "EXTRACTED", "source_file": "/Users/lion/Nutstore Files/\u6211\u7684\u575a\u679c\u4e91/flylion/AI\u9879\u76ee\u5f00\u53d1/\u4e03\u4e2a\u4e60\u60ef\u6668\u8bfb\u8425/backend/src/utils/websocket.js", "source_location": "L24", "weight": 1.0}, {"source": "utils_websocket_websocketmanager_handlemessage", "target": "utils_websocket_websocketmanager_send", "relation": "calls", "context": "call", "confidence": "EXTRACTED", "source_file": "/Users/lion/Nutstore Files/\u6211\u7684\u575a\u679c\u4e91/flylion/AI\u9879\u76ee\u5f00\u53d1/\u4e03\u4e2a\u4e60\u60ef\u6668\u8bfb\u8425/backend/src/utils/websocket.js", "source_location": "L88", "weight": 1.0}, {"source": "utils_websocket_websocketmanager_pushnotificationtouser", "target": "utils_websocket_websocketmanager_publishtootherinstances", "relation": "calls", "context": "call", "confidence": "EXTRACTED", "source_file": "/Users/lion/Nutstore Files/\u6211\u7684\u575a\u679c\u4e91/flylion/AI\u9879\u76ee\u5f00\u53d1/\u4e03\u4e2a\u4e60\u60ef\u6668\u8bfb\u8425/backend/src/utils/websocket.js", "source_location": "L151", "weight": 1.0}, {"source": "utils_websocket_websocketmanager_pushnotificationtotenant", "target": "utils_websocket_websocketmanager_publishtootherinstances", "relation": "calls", "context": "call", "confidence": "EXTRACTED", "source_file": "/Users/lion/Nutstore Files/\u6211\u7684\u575a\u679c\u4e91/flylion/AI\u9879\u76ee\u5f00\u53d1/\u4e03\u4e2a\u4e60\u60ef\u6668\u8bfb\u8425/backend/src/utils/websocket.js", "source_location": "L162", "weight": 1.0}], "raw_calls": [{"caller_nid": "utils_websocket_websocketmanager_installauthandconnection", "callee": "on", "is_member_call": true, "source_file": "/Users/lion/Nutstore Files/\u6211\u7684\u575a\u679c\u4e91/flylion/AI\u9879\u76ee\u5f00\u53d1/\u4e03\u4e2a\u4e60\u60ef\u6668\u8bfb\u8425/backend/src/utils/websocket.js", "source_location": "L30"}, {"caller_nid": "utils_websocket_websocketmanager_send", "callee": "send", "is_member_call": true, "source_file": "/Users/lion/Nutstore Files/\u6211\u7684\u575a\u679c\u4e91/flylion/AI\u9879\u76ee\u5f00\u53d1/\u4e03\u4e2a\u4e60\u60ef\u6668\u8bfb\u8425/backend/src/utils/websocket.js", "source_location": "L80"}, {"caller_nid": "utils_websocket_websocketmanager_send", "callee": "stringify", "is_member_call": true, "source_file": "/Users/lion/Nutstore Files/\u6211\u7684\u575a\u679c\u4e91/flylion/AI\u9879\u76ee\u5f00\u53d1/\u4e03\u4e2a\u4e60\u60ef\u6668\u8bfb\u8425/backend/src/utils/websocket.js", "source_location": "L80"}, {"caller_nid": "utils_websocket_websocketmanager_handlemessage", "callee": "parse", "is_member_call": true, "source_file": "/Users/lion/Nutstore Files/\u6211\u7684\u575a\u679c\u4e91/flylion/AI\u9879\u76ee\u5f00\u53d1/\u4e03\u4e2a\u4e60\u60ef\u6668\u8bfb\u8425/backend/src/utils/websocket.js", "source_location": "L86"}, {"caller_nid": "utils_websocket_websocketmanager_handlemessage", "callee": "toString", "is_member_call": true, "source_file": "/Users/lion/Nutstore Files/\u6211\u7684\u575a\u679c\u4e91/flylion/AI\u9879\u76ee\u5f00\u53d1/\u4e03\u4e2a\u4e60\u60ef\u6668\u8bfb\u8425/backend/src/utils/websocket.js", "source_location": "L86"}, {"caller_nid": "utils_websocket_websocketmanager_handlemessage", "callee": "get", "is_member_call": true, "source_file": "/Users/lion/Nutstore Files/\u6211\u7684\u575a\u679c\u4e91/flylion/AI\u9879\u76ee\u5f00\u53d1/\u4e03\u4e2a\u4e60\u60ef\u6668\u8bfb\u8425/backend/src/utils/websocket.js", "source_location": "L90"}, {"caller_nid": "utils_websocket_websocketmanager_handlemessage", "callee": "catch", "is_member_call": true, "source_file": "/Users/lion/Nutstore Files/\u6211\u7684\u575a\u679c\u4e91/flylion/AI\u9879\u76ee\u5f00\u53d1/\u4e03\u4e2a\u4e60\u60ef\u6668\u8bfb\u8425/backend/src/utils/websocket.js", "source_location": "L93"}, {"caller_nid": "utils_websocket_websocketmanager_handlemessage", "callee": "resolve", "is_member_call": true, "source_file": "/Users/lion/Nutstore Files/\u6211\u7684\u575a\u679c\u4e91/flylion/AI\u9879\u76ee\u5f00\u53d1/\u4e03\u4e2a\u4e60\u60ef\u6668\u8bfb\u8425/backend/src/utils/websocket.js", "source_location": "L93"}, {"caller_nid": "utils_websocket_websocketmanager_handlemessage", "callee": "runWithTenant", "is_member_call": false, "source_file": "/Users/lion/Nutstore Files/\u6211\u7684\u575a\u679c\u4e91/flylion/AI\u9879\u76ee\u5f00\u53d1/\u4e03\u4e2a\u4e60\u60ef\u6668\u8bfb\u8425/backend/src/utils/websocket.js", "source_location": "L94"}, {"caller_nid": "utils_websocket_websocketmanager_handleclose", "callee": "get", "is_member_call": true, "source_file": "/Users/lion/Nutstore Files/\u6211\u7684\u575a\u679c\u4e91/flylion/AI\u9879\u76ee\u5f00\u53d1/\u4e03\u4e2a\u4e60\u60ef\u6668\u8bfb\u8425/backend/src/utils/websocket.js", "source_location": "L108"}, {"caller_nid": "utils_websocket_websocketmanager_handleclose", "callee": "get", "is_member_call": true, "source_file": "/Users/lion/Nutstore Files/\u6211\u7684\u575a\u679c\u4e91/flylion/AI\u9879\u76ee\u5f00\u53d1/\u4e03\u4e2a\u4e60\u60ef\u6668\u8bfb\u8425/backend/src/utils/websocket.js", "source_location": "L112"}, {"caller_nid": "utils_websocket_websocketmanager_handleclose", "callee": "delete", "is_member_call": true, "source_file": "/Users/lion/Nutstore Files/\u6211\u7684\u575a\u679c\u4e91/flylion/AI\u9879\u76ee\u5f00\u53d1/\u4e03\u4e2a\u4e60\u60ef\u6668\u8bfb\u8425/backend/src/utils/websocket.js", "source_location": "L114"}, {"caller_nid": "utils_websocket_websocketmanager_handleclose", "callee": "delete", "is_member_call": true, "source_file": "/Users/lion/Nutstore Files/\u6211\u7684\u575a\u679c\u4e91/flylion/AI\u9879\u76ee\u5f00\u53d1/\u4e03\u4e2a\u4e60\u60ef\u6668\u8bfb\u8425/backend/src/utils/websocket.js", "source_location": "L115"}, {"caller_nid": "utils_websocket_websocketmanager_handleclose", "callee": "get", "is_member_call": true, "source_file": "/Users/lion/Nutstore Files/\u6211\u7684\u575a\u679c\u4e91/flylion/AI\u9879\u76ee\u5f00\u53d1/\u4e03\u4e2a\u4e60\u60ef\u6668\u8bfb\u8425/backend/src/utils/websocket.js", "source_location": "L117"}, {"caller_nid": "utils_websocket_websocketmanager_handleclose", "callee": "delete", "is_member_call": true, "source_file": "/Users/lion/Nutstore Files/\u6211\u7684\u575a\u679c\u4e91/flylion/AI\u9879\u76ee\u5f00\u53d1/\u4e03\u4e2a\u4e60\u60ef\u6668\u8bfb\u8425/backend/src/utils/websocket.js", "source_location": "L119"}, {"caller_nid": "utils_websocket_websocketmanager_handleclose", "callee": "delete", "is_member_call": true, "source_file": "/Users/lion/Nutstore Files/\u6211\u7684\u575a\u679c\u4e91/flylion/AI\u9879\u76ee\u5f00\u53d1/\u4e03\u4e2a\u4e60\u60ef\u6668\u8bfb\u8425/backend/src/utils/websocket.js", "source_location": "L120"}, {"caller_nid": "utils_websocket_websocketmanager_handleclose", "callee": "info", "is_member_call": true, "source_file": "/Users/lion/Nutstore Files/\u6211\u7684\u575a\u679c\u4e91/flylion/AI\u9879\u76ee\u5f00\u53d1/\u4e03\u4e2a\u4e60\u60ef\u6668\u8bfb\u8425/backend/src/utils/websocket.js", "source_location": "L122"}, {"caller_nid": "utils_websocket_websocketmanager_installheartbeat", "callee": "setInterval", "is_member_call": false, "source_file": "/Users/lion/Nutstore Files/\u6211\u7684\u575a\u679c\u4e91/flylion/AI\u9879\u76ee\u5f00\u53d1/\u4e03\u4e2a\u4e60\u60ef\u6668\u8bfb\u8425/backend/src/utils/websocket.js", "source_location": "L128"}, {"caller_nid": "utils_websocket_websocketmanager_installheartbeat", "callee": "on", "is_member_call": true, "source_file": "/Users/lion/Nutstore Files/\u6211\u7684\u575a\u679c\u4e91/flylion/AI\u9879\u76ee\u5f00\u53d1/\u4e03\u4e2a\u4e60\u60ef\u6668\u8bfb\u8425/backend/src/utils/websocket.js", "source_location": "L139"}, {"caller_nid": "utils_websocket_websocketmanager_pushnotificationtouser", "callee": "get", "is_member_call": true, "source_file": "/Users/lion/Nutstore Files/\u6211\u7684\u575a\u679c\u4e91/flylion/AI\u9879\u76ee\u5f00\u53d1/\u4e03\u4e2a\u4e60\u60ef\u6668\u8bfb\u8425/backend/src/utils/websocket.js", "source_location": "L145"}, {"caller_nid": "utils_websocket_websocketmanager_pushnotificationtouser", "callee": "toISOString", "is_member_call": true, "source_file": "/Users/lion/Nutstore Files/\u6211\u7684\u575a\u679c\u4e91/flylion/AI\u9879\u76ee\u5f00\u53d1/\u4e03\u4e2a\u4e60\u60ef\u6668\u8bfb\u8425/backend/src/utils/websocket.js", "source_location": "L146"}, {"caller_nid": "utils_websocket_websocketmanager_pushnotificationtouser", "callee": "forEach", "is_member_call": true, "source_file": "/Users/lion/Nutstore Files/\u6211\u7684\u575a\u679c\u4e91/flylion/AI\u9879\u76ee\u5f00\u53d1/\u4e03\u4e2a\u4e60\u60ef\u6668\u8bfb\u8425/backend/src/utils/websocket.js", "source_location": "L149"}, {"caller_nid": "utils_websocket_websocketmanager_pushnotificationtotenant", "callee": "get", "is_member_call": true, "source_file": "/Users/lion/Nutstore Files/\u6211\u7684\u575a\u679c\u4e91/flylion/AI\u9879\u76ee\u5f00\u53d1/\u4e03\u4e2a\u4e60\u60ef\u6668\u8bfb\u8425/backend/src/utils/websocket.js", "source_location": "L156"}, {"caller_nid": "utils_websocket_websocketmanager_pushnotificationtotenant", "callee": "toISOString", "is_member_call": true, "source_file": "/Users/lion/Nutstore Files/\u6211\u7684\u575a\u679c\u4e91/flylion/AI\u9879\u76ee\u5f00\u53d1/\u4e03\u4e2a\u4e60\u60ef\u6668\u8bfb\u8425/backend/src/utils/websocket.js", "source_location": "L157"}, {"caller_nid": "utils_websocket_websocketmanager_pushnotificationtotenant", "callee": "forEach", "is_member_call": true, "source_file": "/Users/lion/Nutstore Files/\u6211\u7684\u575a\u679c\u4e91/flylion/AI\u9879\u76ee\u5f00\u53d1/\u4e03\u4e2a\u4e60\u60ef\u6668\u8bfb\u8425/backend/src/utils/websocket.js", "source_location": "L160"}, {"caller_nid": "utils_websocket_websocketmanager_isuseronline", "callee": "get", "is_member_call": true, "source_file": "/Users/lion/Nutstore Files/\u6211\u7684\u575a\u679c\u4e91/flylion/AI\u9879\u76ee\u5f00\u53d1/\u4e03\u4e2a\u4e60\u60ef\u6668\u8bfb\u8425/backend/src/utils/websocket.js", "source_location": "L167"}, {"caller_nid": "utils_websocket_websocketmanager_getusersocketcount", "callee": "get", "is_member_call": true, "source_file": "/Users/lion/Nutstore Files/\u6211\u7684\u575a\u679c\u4e91/flylion/AI\u9879\u76ee\u5f00\u53d1/\u4e03\u4e2a\u4e60\u60ef\u6668\u8bfb\u8425/backend/src/utils/websocket.js", "source_location": "L172"}, {"caller_nid": "utils_websocket_websocketmanager_getonlineusers", "callee": "from", "is_member_call": true, "source_file": "/Users/lion/Nutstore Files/\u6211\u7684\u575a\u679c\u4e91/flylion/AI\u9879\u76ee\u5f00\u53d1/\u4e03\u4e2a\u4e60\u60ef\u6668\u8bfb\u8425/backend/src/utils/websocket.js", "source_location": "L181"}, {"caller_nid": "utils_websocket_websocketmanager_getonlineusers", "callee": "keys", "is_member_call": true, "source_file": "/Users/lion/Nutstore Files/\u6211\u7684\u575a\u679c\u4e91/flylion/AI\u9879\u76ee\u5f00\u53d1/\u4e03\u4e2a\u4e60\u60ef\u6668\u8bfb\u8425/backend/src/utils/websocket.js", "source_location": "L181"}, {"caller_nid": "utils_websocket_websocketmanager_getstats", "callee": "forEach", "is_member_call": true, "source_file": "/Users/lion/Nutstore Files/\u6211\u7684\u575a\u679c\u4e91/flylion/AI\u9879\u76ee\u5f00\u53d1/\u4e03\u4e2a\u4e60\u60ef\u6668\u8bfb\u8425/backend/src/utils/websocket.js", "source_location": "L186"}, {"caller_nid": "utils_websocket_websocketmanager_getstats", "callee": "toFixed", "is_member_call": true, "source_file": "/Users/lion/Nutstore Files/\u6211\u7684\u575a\u679c\u4e91/flylion/AI\u9879\u76ee\u5f00\u53d1/\u4e03\u4e2a\u4e60\u60ef\u6668\u8bfb\u8425/backend/src/utils/websocket.js", "source_location": "L193"}]}